CHANGES.rst
CONTRIBUTING.rst
MANIFEST.in
README.rst
setup.py
docs/LICENSE.txt
plone/__init__.py
plone.openid.egg-info/PKG-INFO
plone.openid.egg-info/SOURCES.txt
plone.openid.egg-info/dependency_links.txt
plone.openid.egg-info/namespace_packages.txt
plone.openid.egg-info/not-zip-safe
plone.openid.egg-info/requires.txt
plone.openid.egg-info/top_level.txt
plone/openid/__init__.py
plone/openid/config.py
plone/openid/configure.zcml
plone/openid/django_random.py
plone/openid/interfaces.py
plone/openid/store.py
plone/openid/util.py
plone/openid/plugins/__init__.py
plone/openid/plugins/oid.py
plone/openid/tests/__init__.py
plone/openid/tests/consumer.py
plone/openid/tests/pas.txt
plone/openid/tests/store.txt
plone/openid/tests/testAuthentication.py
plone/openid/tests/testDocTests.py
plone/openid/tests/testExtraction.py
plone/openid/tests/utils.py
plone/openid/www/openid.png
plone/openid/www/openidAdd.zpt